harf/cli.py
harf/jsonf.py
harf/correlations/envs.py
harf/correlations/obsidian.py
harf/correlations/paths.py
harf/grouping/by_comment.py
harf-0.1.1.dist-info/LICENSE
harf-0.1.1.dist-info/METADATA
harf-0.1.1.dist-info/WHEEL
harf-0.1.1.dist-info/entry_points.txt
harf-0.1.1.dist-info/top_level.txt
harf-0.1.1.dist-info/RECORD
