Metadata-Version: 2.1
Name: harf
Version: 0.1.1
Summary: Tools for processing har files
Author-email: Brendan <brendandeleeuw@gmail.com>
License: MIT License        
Project-URL: Homepage, https://github.com/MystiriodisLykos/harf/tree/v0.1.1
Classifier: Programming Language :: Python
Classifier: Programming Language :: Python :: 3
Requires-Python: >=3.8
License-File: LICENSE
Requires-Dist: Click
Requires-Dist: pyserde
Requires-Dist: harf-serde
